lasp_ase/__init__.py
lasp_ase/lasp.py
lasp_ase-0.0.3.dist-info/licenses/LICENSE
lasp_ase-0.0.3.dist-info/METADATA
lasp_ase-0.0.3.dist-info/WHEEL
lasp_ase-0.0.3.dist-info/top_level.txt
lasp_ase-0.0.3.dist-info/RECORD
