Metadata-Version: 2.4
Name: lasp_ase
Version: 0.0.3
Summary: ASE calculator for LASP
Home-page: https://github.com/renpj/lasp_ase
Author: 
Classifier: Programming Language :: Python :: 3
Classifier: Operating System :: OS Independent
License-File: LICENSE
Requires-Dist: ase
Dynamic: classifier
Dynamic: description
Dynamic: description-content-type
Dynamic: home-page
Dynamic: license-file
Dynamic: requires-dist
Dynamic: summary
